bit_ds-0.1.2.dist-info/METADATA
bit_ds-0.1.2.dist-info/WHEEL
bit_ds-0.1.2.dist-info/licenses/LICENSE
bit_ds/__init__.py
bit_ds/bit_ds.pypy311-pp73-x86-linux-gnu.so
bit_ds-0.1.2.dist-info/RECORD
