Metadata-Version: 2.4
Name: bit_ds
Version: 0.1.2
Classifier: Programming Language :: Rust
Classifier: Programming Language :: Python :: Implementation :: CPython
Classifier: Programming Language :: Python :: Implementation :: PyPy
License-File: LICENSE
Summary: A Python library for the Binary Indexed Tree data structure.
Keywords: binary indexed tree,fenwick tree,data structure,python,BIT,pyo3,rust
Author-email: Slug-Boi <github.unshipped609@slmail.me>, August-Brandt <augustbrandt170@gmail.com>
Maintainer-email: Slug-Boi <github.unshipped609@slmail.me>
License: MIT
Requires-Python: >=3.8
